<?xml version="1.0" encoding="UTF-8"?>
<con:testSuite id="d0a92acc-62ba-498d-8d44-2224a265ffea" name="TestSuite 1" xmlns:con="http://eviware.com/soapui/config"><con:settings/><con:runType>SEQUENTIAL</con:runType><con:testCase id="7df62152-80ee-450a-bd11-85535ae750dd" failOnError="true" failTestCaseOnErrors="true" keepSession="false" maxResults="0" name="TestCase 1" searchProperties="true"><con:settings/><con:testStep type="restrequest" name="REST Request" id="826541b1-046f-4d16-aa48-49e1203cb966"><con:settings/><con:config service="http://localhost:8080" resourcePath="/restwindmolenservice/rest/Windmolen/" methodName="Windmolen 1" xsi:type="con:RestRequestStep" xmlns:xsi="http://www.w3.org/2001/XMLSchema-instance"><con:restRequest name="REST Request" id="2b57bb58-a578-4c39-afa8-025444146f14" mediaType="application/json" postQueryString="false"><con:settings><con:setting id="com.eviware.soapui.impl.wsdl.WsdlRequest@request-headers">&lt;xml-fragment/></con:setting></con:settings><con:endpoint>http://localhost:8080</con:endpoint><con:request/><con:originalUri>http://localhost/restwindmolenservice/rest/Windmolen</con:originalUri><con:credentials><con:authType>No Authorization</con:authType></con:credentials><con:jmsConfig JMSDeliveryMode="PERSISTENT"/><con:jmsPropertyConfig/><con:parameters>
  <con:entry key="diameter" value="3"/>
  <con:entry key="mps" value="2"/>
</con:parameters><con:parameterOrder><con:entry>mps</con:entry><con:entry>diameter</con:entry><con:entry>constante</con:entry></con:parameterOrder></con:restRequest></con:config></con:testStep><con:testStep type="restrequest" name="REST Request 1" id="eb0fb0c0-9078-455d-b245-e5b12484e8ee"><con:settings/><con:config service="http://localhost:8080" methodName="Windmolen 1" resourcePath="/restwindmolenservice/rest/Windmolen/" xsi:type="con:RestRequestStep" xmlns:xsi="http://www.w3.org/2001/XMLSchema-instance"><con:restRequest name="REST Request" id="fc803cf8-80be-4275-b430-3f7b7b954537" mediaType="application/json" postQueryString="false"><con:settings/><con:encoding>UTF-8</con:encoding><con:endpoint>http://localhost:8080</con:endpoint><con:request/><con:originalUri>http://localhost/restwindmolenservice/rest/Windmolen/</con:originalUri><con:credentials><con:authType>No Authorization</con:authType></con:credentials><con:jmsConfig JMSDeliveryMode="PERSISTENT"/><con:jmsPropertyConfig/><con:parameters/></con:restRequest></con:config></con:testStep><con:properties/></con:testCase><con:properties/></con:testSuite>